dask_checkpoint/__init__.py
dask_checkpoint/encoder.py
dask_checkpoint/hasher.py
dask_checkpoint/storage.py
dask_checkpoint/task.py
dask_checkpoint/serializer/__init__.py
dask_checkpoint/serializer/numpy.py
dask_checkpoint/serializer/pandas.py
dask_checkpoint/test/__init__.py
dask_checkpoint/test/test_hasher.py
dask_checkpoint/test/test_storage.py
dask_checkpoint/test/test_task.py
dask_checkpoint-0.2.1.dist-info/LICENSE
dask_checkpoint-0.2.1.dist-info/METADATA
dask_checkpoint-0.2.1.dist-info/WHEEL
dask_checkpoint-0.2.1.dist-info/top_level.txt
dask_checkpoint-0.2.1.dist-info/RECORD
