Metadata-Version: 2.1
Name: dask-checkpoint
Version: 0.2.1
Summary: Customizable caching of Dask-delayed.
Home-page: https://github.com/maurosilber/dask-checkpoint
Author: Mauro Silberberg
Author-email: maurosilber@gmail.com
License: MIT
Keywords: dask,cache,caching,checkpoint
Requires-Python: >=3.7
License-File: LICENSE
Requires-Dist: cloudpickle
Requires-Dist: dask
Requires-Dist: fsspec
Requires-Dist: zstandard
Requires-Dist: typing-extensions ; python_version < "3.10"
Provides-Extra: dev
Requires-Dist: hypothesis ; extra == 'dev'
Requires-Dist: pre-commit ; extra == 'dev'
Requires-Dist: pytest ; extra == 'dev'
Requires-Dist: serialize ; extra == 'dev'
Requires-Dist: tox ; extra == 'dev'
